[
  {
    "Name": " Камень бессмертных",
    "Price": {
      "Buy": "33 700",
      "Sell": "34 835"
    },
    "Link": "https://pwcats.info/lisichka/11208"
  },
  {
    "Name": " Печать небожителей",
    "Price": {
      "Buy": "30 300",
      "Sell": "42 800"
    },
    "Link": "https://pwcats.info/lisichka/28061"
  },
  {
    "Name": " Знак Боевой песни",
    "Price": {
      "Buy": "4 100",
      "Sell": "6 400"
    },
    "Link": "https://pwcats.info/lisichka/24633"
  },
  {
    "Name": " Серебряная монета",
    "Price": {
      "Buy": "35 600",
      "Sell": "37 000"
    },
    "Link": "https://pwcats.info/lisichka/41375"
  },
  {
    "Name": " Знак Боевой песни",
    "Price": {
      "Buy": "4 100",
      "Sell": "6 400"
    },
    "Link": "https://pwcats.info/lisichka/24633"
  },
  {
    "Name": " Знак Боевой песни",
    "Price": {
      "Buy": "4 100",
      "Sell": "6 400"
    },
    "Link": "https://pwcats.info/lisichka/24633"
  },
  {
    "Name": " Чудесный кристалл",
    "Price": {
      "Buy": "56 150",
      "Sell": "69 770"
    },
    "Link": "https://pwcats.info/lisichka/25821"
  },
  {
    "Name": " Знак Боевой песни",
    "Price": {
      "Buy": "4 100",
      "Sell": "6 400"
    },
    "Link": "https://pwcats.info/lisichka/24633"
  },
  {
    "Name": " Фрагмент кровавого камня (небо)",
    "Price": {
      "Buy": "216 100",
      "Sell": "270 000"
    },
    "Link": "https://pwcats.info/lisichka/50249"
  }
]